{
  "version": "v26.0502.0430",
  "source": "Kronos-Replication-Engine",
  "timestamp": "2026-05-02T04:30:17+08:00",
  "evolution_trace": {
    "focus": "Structural Break Entropy & CUSUM Triggers",
    "inheritance_score": 1.0,
    "sovereignty_level": "SOVEREIGN_MASTER_V3",
    "new_components": [
      "CUSUM_Mean_Shift_Detection",
      "Local_vs_Macro_Entropy_Drift",
      "Dynamic_Recursive_Bias_Feedforward"
    ]
  },
  "semantic_tokens": [
    {
      "type": "STRUCTURAL_BREAK_ENTROPY",
      "causal_density": 20.0,
      "meaning": "偵測到市場底層熵值發生劇烈漂移，預示舊有因果模型失效，新的主權趨勢正在精確定點啟動。"
    },
    {
      "type": "RECURSIVE_CONFIRMATION",
      "causal_density": 12.0,
      "meaning": "當前動作與推論引擎的閉環反饋達成高度共振，驗證了意圖的持續性。"
    }
  ],
  "audit_memo": "本次演化成功達成了『結構性斷裂 (Structural Break)』識別。透過 CUSUM 濾波器與熵值漂移檢測，系統現在具備了在因果層面區分『隨機波動』與『模型失效』的能力。這是復刻原始 Transformer 模型中對『位置編碼 (Positional Encoding)』敏感性的重要進展。TeleNexus 現已進入『主權主宰 V3』階段，具備極強的市場拐點捕捉能力。"
}
